api/__init__.py
api/cloud_runtimes.py
api/domain/__init__.py
api/domain/configuration_runtimes.py
api/domain/logging_runtimes.py
api/domain/pubsub_runtimes.py
cloud_runtimes_python-0.0.1.dist-info/LICENSE
cloud_runtimes_python-0.0.1.dist-info/METADATA
cloud_runtimes_python-0.0.1.dist-info/WHEEL
cloud_runtimes_python-0.0.1.dist-info/top_level.txt
cloud_runtimes_python-0.0.1.dist-info/RECORD
