Metadata-Version: 2.1
Name: cloud-runtimes-python
Version: 0.0.1
Summary: Cloud Runtimes API for Python3
Home-page: https://github.com/reactivegroup/cloud-runtimes-python
Author: group.rxcloud
Author-email: wshten@gmail.com
License: UNKNOWN
Platform: UNKNOWN
Classifier: Programming Language :: Python :: 3
Classifier: License :: OSI Approved :: MIT License
Classifier: Operating System :: OS Independent
License-File: LICENSE
